ckanext/__init__.py
ckanext/needupdate/__init__.py
ckanext/needupdate/controller.py
ckanext/needupdate/plugin.py
ckanext/needupdate/templates/home/index.html
ckanext/needupdate/templates/user/plugins_dashboard.html
ckanext/needupdate/tests/__init__.py
ckanext/needupdate/tests/test_controller.py
ckanext/needupdate/tests/test_plugin.py
ckanext_needupdate-0.0.1.dist-info/DESCRIPTION.rst
ckanext_needupdate-0.0.1.dist-info/METADATA
ckanext_needupdate-0.0.1.dist-info/RECORD
ckanext_needupdate-0.0.1.dist-info/WHEEL
ckanext_needupdate-0.0.1.dist-info/entry_points.txt
ckanext_needupdate-0.0.1.dist-info/metadata.json
ckanext_needupdate-0.0.1.dist-info/pbr.json
ckanext_needupdate-0.0.1.dist-info/top_level.txt
