Metadata-Version: 2.0
Name: ckanext-needupdate
Version: 0.0.1
Summary: "Extension de CKAN para chequear si las extensiones instaladas, requieren ser actualizadas
Home-page: https://github.com/josesalgado1024/ckanext-needupdate
Author: "Jose A. Salgado"
Author-email: "jose.salgado.wrk@gmail.com"
License: MIT
Keywords: CKAN "ckanext update CKAN"
Platform: UNKNOWN
Classifier: Development Status :: 4 - Beta
Classifier: License :: OSI Approved :: GNU Affero General Public License v3 or later (AGPLv3+)
Classifier: Programming Language :: Python :: 2.7
